{"Direct":false,"Event":[{"Key":0,"Value":[{"B":false,"C":1.65,"I":107043074,"P":6.5,"S":"Количество титулов Финала Мирового Тура Тотал 6.5 Б","T":2117},{"B":false,"C":2.15,"I":107043074,"P":6.5,"S":"Количество титулов Финала Мирового Тура Тотал 6.5 М","T":2118},{"B":false,"C":2.6,"I":107028532,"P":1,"S":"Количество титулов ATP. Ролан Гаррос тотал ровно 1","T":8410},{"B":false,"C":1.6,"I":107028532,"P":2,"S":"Количество титулов ATP. Ролан Гаррос тотал ровно 2","T":8410},{"B":false,"C":5,"I":107028532,"P":3,"S":"Количество титулов ATP. Ролан Гаррос тотал ровно 3","T":8410},{"B":false,"C":2.5,"I":107043676,"P":3,"S":"Количество титулов Открытого Чемпионата США тотал ровно 3","T":8410},{"B":false,"C":20,"I":107028532,"P":4,"S":"Количество титулов ATP. Ролан Гаррос тотал ровно 4","T":8410},{"B":false,"C":2.2,"I":107043676,"P":4,"S":"Количество титулов Открытого Чемпионата США тотал ровно 4","T":8410},{"B":false,"C":50,"I":107028532,"P":5,"S":"Количество титулов ATP. Ролан Гаррос тотал ровно 5","T":8410},{"B":false,"C":4,"I":107043676,"P":5,"S":"Количество титулов Открытого Чемпионата США тотал ровно 5","T":8410},{"B":false,"C":12,"I":107043676,"P":6,"S":"Количество титулов Открытого Чемпионата США тотал ровно 6","T":8410},{"B":false,"C":30,"I":107043676,"P":7,"S":"Количество титулов Открытого Чемпионата США тотал ровно 7","T":8410},{"B":false,"C":8,"I":107028534,"P":8,"S":"Количество титулов Открытый Чемпионат Австралии тотал ровно 8","T":8410},{"B":false,"C":2,"I":107028534,"P":9,"S":"Количество титулов Открытый Чемпионат Австралии тотал ровно 9","T":8410},{"B":false,"C":2.5,"I":107028534,"P":10,"S":"Количество титулов Открытый Чемпионат Австралии тотал ровно 10","T":8410},{"B":false,"C":5.5,"I":107028534,"P":11,"S":"Количество титулов Открытый Чемпионат Австралии тотал ровно 11","T":8410},{"B":false,"C":10,"I":107028534,"P":12,"S":"Количество титулов Открытый Чемпионат Австралии тотал ровно 12","T":8410},{"B":false,"C":30,"I":107028534,"P":13,"S":"Количество титулов Открытый Чемпионат Австралии тотал ровно 13","T":8410}]}],"Liga":"Игроки. Специальное","Opp1":"Новак Джокович. Специальные ставки","Opp2":"","Sport":"Теннис","Start":"\/Date(1604829600000)\/","Uri":"\/line\/Tennis\/1751984-Player-Specials\/76228310-Novak-Djokovic-Special-bets\/","Uri1X":"https:\/\/1x-bet92402.com\/line\/Tennis\/1751984-Player-Specials\/76228310-Novak-Djokovic-Special-bets\/"}