{"Direct":false,"Event":[{"Key":0,"Value":[{"B":false,"C":8,"I":1059463,"P":0,"S":"Победит Серена Уильямс - Да","T":835},{"B":false,"C":100,"I":1059511,"P":0,"S":"Победит Симона Халеп - Да","T":835},{"B":false,"C":6,"I":1206607,"P":0,"S":"Победит Кики Бертенс - Да","T":835},{"B":false,"C":6,"I":1206689,"P":0,"S":"Победит Эшли Барти - Да","T":835},{"B":false,"C":5,"I":1212617,"P":0,"S":"Победит Каролина Плишкова - Да","T":835},{"B":false,"C":8,"I":10338009,"P":0,"S":"Победит Гарбин Мугуруса - Да","T":835},{"B":false,"C":100,"I":14844495,"P":0,"S":"Победит Мария Саккари - Да","T":835},{"B":false,"C":6,"I":15741251,"P":0,"S":"Победит Наоми Осака - Да","T":835},{"B":false,"C":12,"I":17750101,"P":0,"S":"Победит Элиза Мертенс - Да","T":835},{"B":false,"C":7,"I":78785319,"P":0,"S":"Победит Елена Рыбакина - Да","T":835},{"B":false,"C":10,"I":82010299,"P":0,"S":"Победит Арина Соболенко - Да","T":835}]}],"Liga":"WTA. Ролан Гаррос. 2020. Специальные ставки","Opp1":"WTA. Ролан Гаррос. 2020. Наибольшее количество эйсов","Opp2":"","Sport":"Теннис","Start":"\/Date(1601809200000)\/","Uri":"\/line\/Tennis\/2098166-WTA-Roland-Garros-2020-Special-bets\/76250374-WTA-Roland-Garros-2020-Most-Aces\/","Uri1X":"https:\/\/1x-bet92402.com\/line\/Tennis\/2098166-WTA-Roland-Garros-2020-Special-bets\/76250374-WTA-Roland-Garros-2020-Most-Aces\/"}