{"Direct":false,"Event":[{"Key":0,"Value":[{"B":false,"C":1.392,"I":336045,"P":0,"S":"Победит Ювентус - Да","T":835},{"B":false,"C":1000,"I":336047,"P":0,"S":"Победит Милан - Да","T":835},{"B":false,"C":1000,"I":336049,"P":0,"S":"Победит Удинезе - Да","T":835},{"B":false,"C":1000,"I":336051,"P":0,"S":"Победит Наполи - Да","T":835},{"B":false,"C":3.82,"I":336055,"P":0,"S":"Победит Лацио - Да","T":835},{"B":false,"C":415,"I":336057,"P":0,"S":"Победит Рома - Да","T":835},{"B":false,"C":1000,"I":336059,"P":0,"S":"Победит Фиорентина - Да","T":835},{"B":false,"C":1000,"I":336065,"P":0,"S":"Победит Кальяри - Да","T":835},{"B":false,"C":53,"I":336071,"P":0,"S":"Победит Аталанта - Да","T":835},{"B":false,"C":1000,"I":336075,"P":0,"S":"Победит Парма - Да","T":835},{"B":false,"C":1000,"I":336077,"P":0,"S":"Победит Болонья - Да","T":835},{"B":false,"C":1000,"I":336079,"P":0,"S":"Победит Торино - Да","T":835},{"B":false,"C":1000,"I":336117,"P":0,"S":"Победит Сассуоло - Да","T":835},{"B":false,"C":1000,"I":819397,"P":0,"S":"Победит Верона - Да","T":835},{"B":false,"C":11,"I":1061649,"P":0,"S":"Победит Интер - Да","T":835},{"B":false,"C":2.77,"I":336045,"P":0,"S":"Победит Ювентус - Нет","T":836},{"B":false,"C":1.23,"I":336055,"P":0,"S":"Победит Лацио - Нет","T":836},{"B":false,"C":1.03,"I":1061649,"P":0,"S":"Победит Интер - Нет","T":836},{"B":false,"C":100,"I":336047,"P":0,"S":"Милан - в четверке - Да","T":3121},{"B":false,"C":25,"I":336051,"P":0,"S":"Наполи - в четверке - Да","T":3121},{"B":false,"C":4.7,"I":336057,"P":0,"S":"Рома - в четверке - Да","T":3121},{"B":false,"C":1000,"I":336065,"P":0,"S":"Кальяри - в четверке - Да","T":3121},{"B":false,"C":1.17,"I":336071,"P":0,"S":"Аталанта - в четверке - Да","T":3121},{"B":false,"C":750,"I":336075,"P":0,"S":"Парма - в четверке - Да","T":3121},{"B":false,"C":1000,"I":336077,"P":0,"S":"Болонья - в четверке - Да","T":3121},{"B":false,"C":250,"I":819397,"P":0,"S":"Верона - в четверке - Да","T":3121},{"B":false,"C":1.02,"I":1061649,"P":0,"S":"Интер - в четверке - Да","T":3121},{"B":false,"C":1.19,"I":336057,"P":0,"S":"Рома - в четверке - Нет","T":3122},{"B":false,"C":5,"I":336071,"P":0,"S":"Аталанта - в четверке - Нет","T":3122},{"B":false,"C":8.4,"I":1061649,"P":0,"S":"Интер - в четверке - Нет","T":3122},{"B":false,"C":2.4,"I":336047,"P":0,"S":"Милан - в шестерке - Да","T":3125},{"B":false,"C":1.87,"I":336051,"P":0,"S":"Наполи - в шестерке - Да","T":3125},{"B":false,"C":1.12,"I":336057,"P":0,"S":"Рома - в шестерке - Да","T":3125},{"B":false,"C":50,"I":336059,"P":0,"S":"Фиорентина - в шестерке - Да","T":3125},{"B":false,"C":30,"I":336065,"P":0,"S":"Кальяри - в шестерке - Да","T":3125},{"B":false,"C":1.02,"I":336071,"P":0,"S":"Аталанта - в шестерке - Да","T":3125},{"B":false,"C":15,"I":336075,"P":0,"S":"Парма - в шестерке - Да","T":3125},{"B":false,"C":20,"I":336077,"P":0,"S":"Болонья - в шестерке - Да","T":3125},{"B":false,"C":70,"I":336079,"P":0,"S":"Торино - в шестерке - Да","T":3125},{"B":false,"C":12,"I":819397,"P":0,"S":"Верона - в шестерке - Да","T":3125},{"B":false,"C":1.57,"I":336047,"P":0,"S":"Милан - в шестерке - Нет","T":3126},{"B":false,"C":1.9,"I":336051,"P":0,"S":"Наполи - в шестерке - Нет","T":3126},{"B":false,"C":6.3,"I":336057,"P":0,"S":"Рома - в шестерке - Нет","T":3126},{"B":false,"C":14,"I":336071,"P":0,"S":"Аталанта - в шестерке - Нет","T":3126},{"B":false,"C":1.01,"I":336075,"P":0,"S":"Парма - в шестерке - Нет","T":3126},{"B":false,"C":1.03,"I":819397,"P":0,"S":"Верона - в шестерке - Нет","T":3126},{"B":false,"C":500,"I":336045,"P":0,"S":"Ювентус забьет наиб. кол-во голов - Да","T":9702},{"B":false,"C":17,"I":336055,"P":0,"S":"Лацио забьет наиб. кол-во голов - Да","T":9702},{"B":false,"C":200,"I":336057,"P":0,"S":"Рома забьет наиб. кол-во голов - Да","T":9702},{"B":false,"C":1.01,"I":336071,"P":0,"S":"Аталанта забьет наиб. кол-во голов - Да","T":9702},{"B":false,"C":500,"I":1061649,"P":0,"S":"Интер забьет наиб. кол-во голов - Да","T":9702},{"B":false,"C":16,"I":336071,"P":0,"S":"Аталанта забьет наиб. кол-во голов - Нет","T":9703},{"B":false,"C":1000,"I":336047,"P":0,"S":"Милан вылетит в сезоне","T":10666},{"B":false,"C":8.5,"I":336049,"P":0,"S":"Удинезе вылетит в сезоне","T":10666},{"B":false,"C":65,"I":336059,"P":0,"S":"Фиорентина вылетит в сезоне","T":10666},{"B":false,"C":150,"I":336065,"P":0,"S":"Кальяри вылетит в сезоне","T":10666},{"B":false,"C":4.7,"I":336067,"P":0,"S":"Дженоа вылетит в сезоне","T":10666},{"B":false,"C":120,"I":336075,"P":0,"S":"Парма вылетит в сезоне","T":10666},{"B":false,"C":150,"I":336077,"P":0,"S":"Болонья вылетит в сезоне","T":10666},{"B":false,"C":10,"I":336079,"P":0,"S":"Торино вылетит в сезоне","T":10666},{"B":false,"C":6.5,"I":336081,"P":0,"S":"Сампдория вылетит в сезоне","T":10666},{"B":false,"C":1.06,"I":336089,"P":0,"S":"Брешиа вылетит в сезоне","T":10666},{"B":false,"C":35,"I":336117,"P":0,"S":"Сассуоло вылетит в сезоне","T":10666},{"B":false,"C":500,"I":819397,"P":0,"S":"Верона вылетит в сезоне","T":10666},{"B":false,"C":1.08,"I":16038933,"P":0,"S":"СПАЛ вылетит в сезоне","T":10666},{"B":false,"C":1.65,"I":17752373,"P":0,"S":"Лечче вылетит в сезоне","T":10666},{"B":false,"C":1.07,"I":336049,"P":0,"S":"Удинезе избежит вылета в сезоне","T":10667},{"B":false,"C":1.19,"I":336067,"P":0,"S":"Дженоа избежит вылета в сезоне","T":10667},{"B":false,"C":1.05,"I":336079,"P":0,"S":"Торино избежит вылета в сезоне","T":10667},{"B":false,"C":1.11,"I":336081,"P":0,"S":"Сампдория избежит вылета в сезоне","T":10667},{"B":false,"C":9.2,"I":336089,"P":0,"S":"Брешиа избежит вылета в сезоне","T":10667},{"B":false,"C":7.9,"I":16038933,"P":0,"S":"СПАЛ избежит вылета в сезоне","T":10667},{"B":false,"C":2.24,"I":17752373,"P":0,"S":"Лечче избежит вылета в сезоне","T":10667},{"B":false,"C":1000,"I":30549291,"P":0,"S":"Наполи - Победит без учета Ювентус - Да","T":12594},{"B":false,"C":25,"I":33480531,"P":0,"S":"Аталанта - Победит без учета Ювентус - Да","T":12594},{"B":false,"C":3.7,"I":53752877,"P":0,"S":"Интер - Победит без учета Ювентус - Да","T":12594},{"B":false,"C":1000,"I":53752881,"P":0,"S":"Милан - Победит без учета Ювентус - Да","T":12594},{"B":false,"C":500,"I":53752885,"P":0,"S":"Рома - Победит без учета Ювентус - Да","T":12594},{"B":false,"C":1.3,"I":53752889,"P":0,"S":"Лацио - Победит без учета Ювентус - Да","T":12594},{"B":false,"C":1.28,"I":53752877,"P":0,"S":"Интер - Победит без учета Ювентус - Нет","T":12595},{"B":false,"C":3.5,"I":53752889,"P":0,"S":"Лацио - Победит без учета Ювентус - Нет","T":12595},{"B":false,"C":550,"I":336047,"P":0,"S":"Милан - в двойке - Да","T":3117},{"B":false,"C":550,"I":336051,"P":0,"S":"Наполи - в двойке - Да","T":3117},{"B":false,"C":1.3,"I":336055,"P":0,"S":"Лацио - в двойке - Да","T":3117},{"B":false,"C":400,"I":336057,"P":0,"S":"Рома - в двойке - Да","T":3117},{"B":false,"C":25,"I":336071,"P":0,"S":"Аталанта - в двойке - Да","T":3117},{"B":false,"C":3.74,"I":1061649,"P":0,"S":"Интер - в двойке - Да","T":3117},{"B":false,"C":3.5,"I":336055,"P":0,"S":"Лацио - в двойке - Нет","T":3118},{"B":false,"C":1.27,"I":1061649,"P":0,"S":"Интер - в двойке - Нет","T":3118}]}],"Liga":"Италия. Победитель","Opp1":"Чемпионат Италии. Серия А. 2019\/20. Победитель","Opp2":"","Sport":"Футбол","Start":"\/Date(1592661600000)\/","Uri":"\/line\/Football\/1756204-Italy-Winner\/76616314-Italy-Serie-A-201920-Winner\/","Uri1X":"https:\/\/1x-bet92402.com\/line\/Football\/1756204-Italy-Winner\/76616314-Italy-Serie-A-201920-Winner\/"}