{"Direct":false,"Event":[{"Key":0,"Value":[{"B":false,"C":1.75,"I":2881,"P":0,"S":"Победит Матьё Вальбуэна - Да","T":835},{"B":false,"C":25,"I":179855,"P":0,"S":"Победит Гхэйас Захид - Да","T":835},{"B":false,"C":6,"I":905445,"P":0,"S":"Победит Петрос Манталос - Да","T":835},{"B":false,"C":4.5,"I":1981859,"P":0,"S":"Победит Иоаннис Фетфацидис - Да","T":835},{"B":false,"C":18,"I":4159033,"P":0,"S":"Победит Даниэле Верде - Да","T":835},{"B":false,"C":8,"I":4371561,"P":0,"S":"Победит Константинос Фортунис - Да","T":835},{"B":false,"C":20,"I":8416299,"P":0,"S":"Победит Диего Бисесвар - Да","T":835},{"B":false,"C":25,"I":9492439,"P":0,"S":"Победит Димитрис Лимниос - Да","T":835},{"B":false,"C":15,"I":82470989,"P":0,"S":"Победит Хавьер Матилья - Да","T":835}]}],"Liga":"Греция. Победитель","Opp1":"Чемпионат Греции. Суперлига 2019\/20. Плей-офф. Какой игрок совершит наибольшее количество голевых передач","Opp2":"","Sport":"Футбол","Start":"\/Date(1593493200000)\/","Uri":"\/line\/Football\/1776901-Greece-Winner\/77178267-Greece-SuperLeague-201920-Play-Offs-Top-Assistman\/","Uri1X":"https:\/\/1x-bet92402.com\/line\/Football\/1776901-Greece-Winner\/77178267-Greece-SuperLeague-201920-Play-Offs-Top-Assistman\/"}