{"Direct":false,"Event":[{"Key":0,"Value":[{"B":false,"C":2.02,"I":null,"P":0,"S":"П1","T":1},{"B":false,"C":3.3,"I":null,"P":0,"S":"Ничья","T":2},{"B":false,"C":3.28,"I":null,"P":0,"S":"П2","T":3},{"B":false,"C":1.49,"I":null,"P":0,"S":"Фора 1 (0)","T":7},{"B":false,"C":2.44,"I":null,"P":0,"S":"Фора 2 (0)","T":8}]}],"Liga":"Чемпионат Польши. Лига 1","Opp1":"МКС Пуща","Opp2":"Олимпия Грудзёндз","Sport":"Футбол","Start":"\/Date(1592658600000)\/","Uri":"\/line\/Football\/30693-Poland-Championship-Liga-1\/77743135-Puszcza-Niepolomice-Olimpia-Grudziadz\/","Uri1X":"https:\/\/1x-bet92402.com\/line\/Football\/30693-Poland-Championship-Liga-1\/77743135-Puszcza-Niepolomice-Olimpia-Grudziadz\/"}